{
  "Moroni 1:4": [
    {
      "index": 1,
      "remove": [
        {
          "text": ",",
          "isWord": false
        }
      ],
      "add": []
    },
    {
      "index": 29,
      "remove": [
        {
          "text": ":",
          "isWord": false
        }
      ],
      "add": [
        {
          "text": ";",
          "isWord": false
        }
      ]
    }
  ],
  "Moroni 2:2": [
    {
      "index": 16,
      "remove": [
        {
          "text": "Ye",
          "isWord": true
        }
      ],
      "add": [
        {
          "text": "ye",
          "isWord": true
        }
      ]
    },
    {
      "index": 45,
      "remove": [
        {
          "text": " ",
          "isWord": false
        },
        {
          "text": "that",
          "isWord": true
        }
      ],
      "add": []
    },
    {
      "index": 112,
      "remove": [
        {
          "text": ":",
          "isWord": false
        }
      ],
      "add": [
        {
          "text": ",",
          "isWord": false
        }
      ]
    }
  ],
  "Moroni 3:1": [
    {
      "index": 11,
      "remove": [
        {
          "text": "which",
          "isWord": true
        }
      ],
      "add": [
        {
          "text": "who",
          "isWord": true
        }
      ]
    },
    {
      "index": 19,
      "remove": [
        {
          "text": "Elders",
          "isWord": true
        }
      ],
      "add": [
        {
          "text": "elders",
          "isWord": true
        }
      ]
    }
  ],
  "Moroni 3:3": [
    {
      "index": 0,
      "remove": [
        {
          "text": "In",
          "isWord": true
        }
      ],
      "add": [
        {
          "text": "in",
          "isWord": true
        }
      ]
    }
  ],
  "Moroni 4:1": [
    {
      "index": 62,
      "remove": [
        {
          "text": "that",
          "isWord": true
        },
        {
          "text": " ",
          "isWord": false
        }
      ],
      "add": []
    },
    {
      "index": 73,
      "remove": [
        {
          "text": ":",
          "isWord": false
        }
      ],
      "add": [
        {
          "text": ";",
          "isWord": false
        }
      ]
    },
    {
      "index": 81,
      "remove": [],
      "add": [
        {
          "text": "or",
          "isWord": true
        },
        {
          "text": " ",
          "isWord": false
        }
      ]
    },
    {
      "index": 85,
      "remove": [
        {
          "text": "minister",
          "isWord": true
        }
      ],
      "add": [
        {
          "text": "administer",
          "isWord": true
        }
      ]
    }
  ],
  "Moroni 6:3": [
    {
      "index": 44,
      "remove": [
        {
          "text": "unto",
          "isWord": true
        }
      ],
      "add": [
        {
          "text": "to",
          "isWord": true
        }
      ]
    }
  ],
  "Moroni 6:4": [
    {
      "index": 3,
      "remove": [
        {
          "text": " ",
          "isWord": false
        },
        {
          "text": "that",
          "isWord": true
        }
      ],
      "add": []
    },
    {
      "index": 15,
      "remove": [
        {
          "text": " ",
          "isWord": false
        },
        {
          "text": "the",
          "isWord": true
        }
      ],
      "add": []
    }
  ],
  "Moroni 6:9": [
    {
      "index": 51,
      "remove": [
        {
          "text": ":",
          "isWord": false
        }
      ],
      "add": [
        {
          "text": ";",
          "isWord": false
        }
      ]
    }
  ],
  "Moroni 7:1": [
    {
      "index": 47,
      "remove": [
        {
          "text": ":",
          "isWord": false
        }
      ],
      "add": [
        {
          "text": ";",
          "isWord": false
        }
      ]
    }
  ],
  "Moroni 7:3": [
    {
      "index": 12,
      "remove": [
        {
          "text": "that",
          "isWord": true
        }
      ],
      "add": [
        {
          "text": "thot",
          "isWord": true
        }
      ]
    },
    {
      "index": 82,
      "remove": [
        {
          "text": "hence",
          "isWord": true
        },
        {
          "text": " ",
          "isWord": false
        },
        {
          "text": "forth",
          "isWord": true
        }
      ],
      "add": [
        {
          "text": "henceforth",
          "isWord": true
        }
      ]
    },
    {
      "index": 101,
      "remove": [
        {
          "text": "Heaven",
          "isWord": true
        }
      ],
      "add": [
        {
          "text": "heaveu",
          "isWord": true
        }
      ]
    }
  ],
  "Moroni 7:4": [
    {
      "index": 40,
      "remove": [
        {
          "text": ":",
          "isWord": false
        }
      ],
      "add": [
        {
          "text": ";",
          "isWord": false
        }
      ]
    }
  ],
  "Moroni 7:5": [
    {
      "index": 20,
      "remove": [
        {
          "text": "By",
          "isWord": true
        }
      ],
      "add": [
        {
          "text": "by",
          "isWord": true
        }
      ]
    },
    {
      "index": 33,
      "remove": [
        {
          "text": ":",
          "isWord": false
        }
      ],
      "add": [
        {
          "text": ";",
          "isWord": false
        }
      ]
    }
  ],
  "Moroni 7:6": [
    {
      "index": 12,
      "remove": [
        {
          "text": "A",
          "isWord": true
        }
      ],
      "add": [
        {
          "text": "a",
          "isWord": true
        }
      ]
    },
    {
      "index": 32,
      "remove": [
        {
          "text": ":",
          "isWord": false
        }
      ],
      "add": [
        {
          "text": ";",
          "isWord": false
        }
      ]
    },
    {
      "index": 75,
      "remove": [
        {
          "text": "profiteth",
          "isWord": true
        }
      ],
      "add": [
        {
          "text": "proffiteth",
          "isWord": true
        }
      ]
    }
  ],
  "Moroni 7:8": [
    {
      "index": 25,
      "remove": [
        {
          "text": "doeth",
          "isWord": true
        }
      ],
      "add": [
        {
          "text": "doth",
          "isWord": true
        }
      ]
    }
  ],
  "Moroni 7:9": [
    {
      "index": 57,
      "remove": [
        {
          "text": ":",
          "isWord": false
        }
      ],
      "add": [
        {
          "text": ";",
          "isWord": false
        }
      ]
    }
  ],
  "Moroni 7:11": [
    {
      "index": 49,
      "remove": [
        {
          "text": "the",
          "isWord": true
        }
      ],
      "add": [
        {
          "text": "a",
          "isWord": true
        }
      ]
    },
    {
      "index": 57,
      "remove": [
        {
          "text": "Devil",
          "isWord": true
        }
      ],
      "add": [
        {
          "text": "devil",
          "isWord": true
        }
      ]
    },
    {
      "index": 92,
      "remove": [
        {
          "text": "Devil",
          "isWord": true
        }
      ],
      "add": [
        {
          "text": "devil",
          "isWord": true
        }
      ]
    }
  ],
  "Moroni 7:12": [
    {
      "index": 38,
      "remove": [
        {
          "text": "Devil",
          "isWord": true
        },
        {
          "text": ":",
          "isWord": false
        }
      ],
      "add": [
        {
          "text": "devil",
          "isWord": true
        },
        {
          "text": ";",
          "isWord": false
        }
      ]
    },
    {
      "index": 45,
      "remove": [
        {
          "text": "Devil",
          "isWord": true
        }
      ],
      "add": [
        {
          "text": "devil",
          "isWord": true
        }
      ]
    }
  ],
  "Moroni 7:14": [
    {
      "index": 66,
      "remove": [
        {
          "text": "Devil",
          "isWord": true
        }
      ],
      "add": [
        {
          "text": "devil",
          "isWord": true
        }
      ]
    }
  ],
  "Moroni 7:15": [
    {
      "index": 90,
      "remove": [
        {
          "text": "—",
          "isWord": false
        }
      ],
      "add": []
    }
  ],
  "Moroni 7:16": [
    {
      "index": 56,
      "remove": [
        {
          "text": ":",
          "isWord": false
        }
      ],
      "add": [
        {
          "text": ";",
          "isWord": false
        }
      ]
    },
    {
      "index": 126,
      "remove": [
        {
          "text": ",",
          "isWord": false
        }
      ],
      "add": []
    }
  ],
  "Moroni 7:17": [
    {
      "index": 68,
      "remove": [
        {
          "text": "Devil",
          "isWord": true
        }
      ],
      "add": [
        {
          "text": "devil",
          "isWord": true
        }
      ]
    },
    {
      "index": 73,
      "remove": [
        {
          "text": "after",
          "isWord": true
        }
      ],
      "add": [
        {
          "text": "afier",
          "isWord": true
        }
      ]
    },
    {
      "index": 83,
      "remove": [
        {
          "text": "Devil",
          "isWord": true
        }
      ],
      "add": [
        {
          "text": "devil",
          "isWord": true
        }
      ]
    },
    {
      "index": 86,
      "remove": [
        {
          "text": ":",
          "isWord": false
        }
      ],
      "add": [
        {
          "text": ",",
          "isWord": false
        }
      ]
    },
    {
      "index": 123,
      "remove": [
        {
          "text": "doth",
          "isWord": true
        }
      ],
      "add": [
        {
          "text": "do",
          "isWord": true
        }
      ]
    },
    {
      "index": 127,
      "remove": [
        {
          "text": "which",
          "isWord": true
        }
      ],
      "add": [
        {
          "text": "who",
          "isWord": true
        }
      ]
    }
  ],
  "Moroni 7:18": [
    {
      "index": 60,
      "remove": [
        {
          "text": ":",
          "isWord": false
        }
      ],
      "add": [
        {
          "text": ";",
          "isWord": false
        }
      ]
    },
    {
      "index": 70,
      "remove": [
        {
          "text": "judgement",
          "isWord": true
        }
      ],
      "add": [
        {
          "text": "judgment",
          "isWord": true
        }
      ]
    }
  ],
  "Moroni 7:25": [
    {
      "index": 80,
      "remove": [
        {
          "text": ":",
          "isWord": false
        }
      ],
      "add": [
        {
          "text": ";",
          "isWord": false
        }
      ]
    }
  ],
  "Moroni 7:26": [
    {
      "index": 54,
      "remove": [
        {
          "text": "suredly",
          "isWord": true
        }
      ],
      "add": [
        {
          "text": "sure",
          "isWord": true
        }
      ]
    },
    {
      "index": 81,
      "remove": [
        {
          "text": "Whatsoever",
          "isWord": true
        }
      ],
      "add": [
        {
          "text": "whatsoever",
          "isWord": true
        }
      ]
    }
  ],
  "Moroni 7:27": [
    {
      "index": 19,
      "remove": [
        {
          "text": "that",
          "isWord": true
        },
        {
          "text": " ",
          "isWord": false
        }
      ],
      "add": []
    },
    {
      "index": 23,
      "remove": [
        {
          "text": "hath",
          "isWord": true
        }
      ],
      "add": [
        {
          "text": "had",
          "isWord": true
        }
      ]
    },
    {
      "index": 86,
      "remove": [
        {
          "text": ":",
          "isWord": false
        }
      ],
      "add": [
        {
          "text": ";",
          "isWord": false
        }
      ]
    }
  ],
  "Moroni 7:28": [
    {
      "index": 29,
      "remove": [
        {
          "text": "that",
          "isWord": true
        }
      ],
      "add": [
        {
          "text": "who",
          "isWord": true
        }
      ]
    },
    {
      "index": 31,
      "remove": [
        {
          "text": "hath",
          "isWord": true
        }
      ],
      "add": [
        {
          "text": "have",
          "isWord": true
        }
      ]
    },
    {
      "index": 44,
      "remove": [
        {
          "text": "that",
          "isWord": true
        }
      ],
      "add": [
        {
          "text": "who",
          "isWord": true
        }
      ]
    },
    {
      "index": 103,
      "remove": [
        {
          "text": "—",
          "isWord": false
        }
      ],
      "add": []
    }
  ],
  "Moroni 7:29": [
    {
      "index": 3,
      "remove": [
        {
          "text": " ",
          "isWord": false
        },
        {
          "text": "that",
          "isWord": true
        }
      ],
      "add": []
    },
    {
      "index": 40,
      "remove": [
        {
          "text": "Nay",
          "isWord": true
        }
      ],
      "add": [
        {
          "text": "nay",
          "isWord": true
        }
      ]
    },
    {
      "index": 45,
      "remove": [
        {
          "text": "hath",
          "isWord": true
        }
      ],
      "add": [
        {
          "text": "have",
          "isWord": true
        }
      ]
    }
  ],
  "Moroni 7:31": [
    {
      "index": 81,
      "remove": [
        {
          "text": "among",
          "isWord": true
        }
      ],
      "add": [
        {
          "text": "amoug",
          "isWord": true
        }
      ]
    }
  ],
  "Moroni 7:32": [
    {
      "index": 72,
      "remove": [
        {
          "text": ":",
          "isWord": false
        }
      ],
      "add": [
        {
          "text": ";",
          "isWord": false
        }
      ]
    }
  ],
  "Moroni 7:33": [
    {
      "index": 9,
      "remove": [
        {
          "text": "If",
          "isWord": true
        }
      ],
      "add": [
        {
          "text": "if",
          "isWord": true
        }
      ]
    }
  ],
  "Moroni 7:34": [
    {
      "index": 9,
      "remove": [
        {
          "text": "Repent",
          "isWord": true
        }
      ],
      "add": [
        {
          "text": "repent",
          "isWord": true
        }
      ]
    }
  ],
  "Moroni 7:35": [
    {
      "index": 95,
      "remove": [
        {
          "text": "hath",
          "isWord": true
        }
      ],
      "add": [
        {
          "text": "has",
          "isWord": true
        }
      ]
    }
  ],
  "Moroni 7:36": [
    {
      "index": 2,
      "remove": [
        {
          "text": "hath",
          "isWord": true
        }
      ],
      "add": [
        {
          "text": "have",
          "isWord": true
        }
      ]
    },
    {
      "index": 22,
      "remove": [
        {
          "text": " ",
          "isWord": false
        }
      ],
      "add": [
        {
          "text": "—",
          "isWord": false
        }
      ]
    },
    {
      "index": 25,
      "remove": [
        {
          "text": "hath",
          "isWord": true
        }
      ],
      "add": [
        {
          "text": "has",
          "isWord": true
        }
      ]
    }
  ],
  "Moroni 7:37": [
    {
      "index": 10,
      "remove": [
        {
          "text": "Nay",
          "isWord": true
        }
      ],
      "add": [
        {
          "text": "nay",
          "isWord": true
        }
      ]
    },
    {
      "index": 105,
      "remove": [
        {
          "text": ":",
          "isWord": false
        }
      ],
      "add": [
        {
          "text": ";",
          "isWord": false
        }
      ]
    }
  ],
  "Moroni 7:38": [
    {
      "index": 41,
      "remove": [
        {
          "text": ";",
          "isWord": false
        }
      ],
      "add": [
        {
          "text": ":",
          "isWord": false
        }
      ]
    },
    {
      "index": 81,
      "remove": [
        {
          "text": ":",
          "isWord": false
        }
      ],
      "add": [
        {
          "text": ";",
          "isWord": false
        }
      ]
    }
  ],
  "Moroni 7:39": [
    {
      "index": 42,
      "remove": [
        {
          "text": ",",
          "isWord": false
        }
      ],
      "add": []
    },
    {
      "index": 51,
      "remove": [
        {
          "text": ":",
          "isWord": false
        }
      ],
      "add": [
        {
          "text": ";",
          "isWord": false
        }
      ]
    }
  ],
  "Moroni 7:41": [
    {
      "index": 30,
      "remove": [
        {
          "text": "That",
          "isWord": true
        }
      ],
      "add": [
        {
          "text": "that",
          "isWord": true
        }
      ]
    }
  ],
  "Moroni 7:42": [
    {
      "index": 23,
      "remove": [
        {
          "text": ":",
          "isWord": false
        }
      ],
      "add": [
        {
          "text": ";",
          "isWord": false
        }
      ]
    }
  ],
  "Moroni 7:43": [
    {
      "index": 3,
      "remove": [
        {
          "text": ":",
          "isWord": false
        }
      ],
      "add": [
        {
          "text": ",",
          "isWord": false
        }
      ]
    },
    {
      "index": 5,
      "remove": [
        {
          "text": "Behold",
          "isWord": true
        }
      ],
      "add": [
        {
          "text": "behold",
          "isWord": true
        }
      ]
    },
    {
      "index": 16,
      "remove": [
        {
          "text": "That",
          "isWord": true
        }
      ],
      "add": [
        {
          "text": "that",
          "isWord": true
        }
      ]
    },
    {
      "index": 49,
      "remove": [
        {
          "text": ":",
          "isWord": false
        }
      ],
      "add": [
        {
          "text": ";",
          "isWord": false
        }
      ]
    }
  ],
  "Moroni 7:44": [
    {
      "index": 41,
      "remove": [
        {
          "text": "of",
          "isWord": true
        }
      ],
      "add": [
        {
          "text": "in",
          "isWord": true
        }
      ]
    },
    {
      "index": 44,
      "remove": [
        {
          "text": ";",
          "isWord": false
        }
      ],
      "add": [
        {
          "text": ",",
          "isWord": false
        }
      ]
    },
    {
      "index": 54,
      "remove": [
        {
          "text": "be",
          "isWord": true
        }
      ],
      "add": [
        {
          "text": "he",
          "isWord": true
        }
      ]
    },
    {
      "index": 106,
      "remove": [
        {
          "text": ":",
          "isWord": false
        }
      ],
      "add": [
        {
          "text": ";",
          "isWord": false
        }
      ]
    }
  ],
  "Moroni 7:47": [
    {
      "index": 15,
      "remove": [
        {
          "text": ",",
          "isWord": false
        }
      ],
      "add": []
    },
    {
      "index": 23,
      "remove": [
        {
          "text": "forever",
          "isWord": true
        }
      ],
      "add": [
        {
          "text": "for ever",
          "isWord": true
        }
      ]
    }
  ],
  "Moroni 7:48": [
    {
      "index": 115,
      "remove": [
        {
          "text": ":",
          "isWord": false
        }
      ],
      "add": [
        {
          "text": ";",
          "isWord": false
        }
      ]
    }
  ],
  "Moroni 8:1": [
    {
      "index": 18,
      "remove": [
        {
          "text": ",",
          "isWord": false
        }
      ],
      "add": []
    },
    {
      "index": 70,
      "remove": [
        {
          "text": ":",
          "isWord": false
        }
      ],
      "add": [
        {
          "text": ",",
          "isWord": false
        }
      ]
    }
  ],
  "Moroni 8:2": [
    {
      "index": 0,
      "remove": [
        {
          "text": "My",
          "isWord": true
        }
      ],
      "add": [
        {
          "text": "my",
          "isWord": true
        }
      ]
    }
  ],
  "Moroni 8:3": [
    {
      "index": 30,
      "remove": [
        {
          "text": ",",
          "isWord": false
        }
      ],
      "add": []
    }
  ],
  "Moroni 8:4": [
    {
      "index": 7,
      "remove": [
        {
          "text": ",",
          "isWord": false
        }
      ],
      "add": []
    },
    {
      "index": 28,
      "remove": [
        {
          "text": ":",
          "isWord": false
        }
      ],
      "add": [
        {
          "text": ";",
          "isWord": false
        }
      ]
    }
  ],
  "Moroni 8:5": [
    {
      "index": 13,
      "remove": [
        {
          "text": ":",
          "isWord": false
        }
      ],
      "add": [
        {
          "text": ",",
          "isWord": false
        }
      ]
    }
  ],
  "Moroni 8:6": [
    {
      "index": 43,
      "remove": [
        {
          "text": ":",
          "isWord": false
        }
      ],
      "add": [
        {
          "text": ";",
          "isWord": false
        }
      ]
    }
  ],
  "Moroni 8:7": [
    {
      "index": 19,
      "remove": [
        {
          "text": ",",
          "isWord": false
        }
      ],
      "add": []
    }
  ],
  "Moroni 8:8": [
    {
      "index": 0,
      "remove": [
        {
          "text": "Listen",
          "isWord": true
        }
      ],
      "add": [
        {
          "text": "listen",
          "isWord": true
        }
      ]
    },
    {
      "index": 42,
      "remove": [
        {
          "text": "not",
          "isWord": true
        }
      ],
      "add": [
        {
          "text": "uot",
          "isWord": true
        }
      ]
    },
    {
      "index": 148,
      "remove": [
        {
          "text": ":",
          "isWord": false
        }
      ],
      "add": [
        {
          "text": ";",
          "isWord": false
        }
      ]
    }
  ],
  "Moroni 8:10": [
    {
      "index": 32,
      "remove": [
        {
          "text": "they",
          "isWord": true
        }
      ],
      "add": [
        {
          "text": "those",
          "isWord": true
        }
      ]
    },
    {
      "index": 34,
      "remove": [
        {
          "text": "which",
          "isWord": true
        }
      ],
      "add": [
        {
          "text": "who",
          "isWord": true
        }
      ]
    },
    {
      "index": 62,
      "remove": [
        {
          "text": "must repent and",
          "isWord": true
        }
      ],
      "add": [
        {
          "text": "mustrepen tand",
          "isWord": true
        }
      ]
    }
  ],
  "Moroni 8:11": [
    {
      "index": 23,
      "remove": [
        {
          "text": "baptism",
          "isWord": true
        }
      ],
      "add": [
        {
          "text": "haptism",
          "isWord": true
        }
      ]
    }
  ],
  "Moroni 8:12": [
    {
      "index": 28,
      "remove": [
        {
          "text": ":",
          "isWord": false
        }
      ],
      "add": [
        {
          "text": ";",
          "isWord": false
        }
      ]
    },
    {
      "index": 65,
      "remove": [
        {
          "text": "to",
          "isWord": true
        }
      ],
      "add": [
        {
          "text": "of",
          "isWord": true
        }
      ]
    },
    {
      "index": 68,
      "remove": [
        {
          "text": ":",
          "isWord": false
        }
      ],
      "add": [
        {
          "text": ";",
          "isWord": false
        }
      ]
    }
  ],
  "Moroni 8:14": [
    {
      "index": 11,
      "remove": [
        {
          "text": "That",
          "isWord": true
        }
      ],
      "add": [
        {
          "text": "that",
          "isWord": true
        }
      ]
    },
    {
      "index": 25,
      "remove": [
        {
          "text": "needeth",
          "isWord": true
        }
      ],
      "add": [
        {
          "text": "need",
          "isWord": true
        }
      ]
    },
    {
      "index": 51,
      "remove": [],
      "add": [
        {
          "text": "of",
          "isWord": true
        },
        {
          "text": " ",
          "isWord": false
        }
      ]
    },
    {
      "index": 52,
      "remove": [
        {
          "text": ":",
          "isWord": false
        }
      ],
      "add": [
        {
          "text": ";",
          "isWord": false
        }
      ]
    }
  ],
  "Moroni 8:16": [
    {
      "index": 83,
      "remove": [
        {
          "text": ":",
          "isWord": false
        }
      ],
      "add": [
        {
          "text": ";",
          "isWord": false
        }
      ]
    }
  ],
  "Moroni 8:20": [
    {
      "index": 14,
      "remove": [
        {
          "text": "needeth",
          "isWord": true
        }
      ],
      "add": [
        {
          "text": "need",
          "isWord": true
        }
      ]
    }
  ],
  "Moroni 8:21": [
    {
      "index": 79,
      "remove": [
        {
          "text": "judgement",
          "isWord": true
        }
      ],
      "add": [
        {
          "text": "judgment",
          "isWord": true
        }
      ]
    }
  ],
  "Moroni 8:24": [
    {
      "index": 12,
      "remove": [
        {
          "text": "had",
          "isWord": true
        }
      ],
      "add": [
        {
          "text": "ought",
          "isWord": true
        }
      ]
    },
    {
      "index": 15,
      "remove": [
        {
          "text": " ",
          "isWord": false
        },
        {
          "text": "ought",
          "isWord": true
        }
      ],
      "add": []
    },
    {
      "index": 21,
      "remove": [
        {
          "text": ":",
          "isWord": false
        }
      ],
      "add": [
        {
          "text": ";",
          "isWord": false
        }
      ]
    },
    {
      "index": 40,
      "remove": [
        {
          "text": ",",
          "isWord": false
        }
      ],
      "add": []
    }
  ],
  "Moroni 8:26": [
    {
      "index": 31,
      "remove": [],
      "add": [
        {
          "text": ",",
          "isWord": false
        }
      ]
    }
  ],
  "Moroni 8:27": [
    {
      "index": 69,
      "remove": [
        {
          "text": "proved",
          "isWord": true
        }
      ],
      "add": [
        {
          "text": "proven",
          "isWord": true
        }
      ]
    }
  ],
  "Moroni 8:28": [
    {
      "index": 15,
      "remove": [],
      "add": [
        {
          "text": " ",
          "isWord": false
        },
        {
          "text": "may",
          "isWord": true
        }
      ]
    }
  ],
  "Moroni 8:29": [
    {
      "index": 35,
      "remove": [
        {
          "text": "of",
          "isWord": true
        }
      ],
      "add": [
        {
          "text": "ef",
          "isWord": true
        }
      ]
    },
    {
      "index": 43,
      "remove": [
        {
          "text": "was",
          "isWord": true
        }
      ],
      "add": [
        {
          "text": "were",
          "isWord": true
        }
      ]
    }
  ],
  "Moroni 9:2": [
    {
      "index": 25,
      "remove": [
        {
          "text": " ",
          "isWord": false
        },
        {
          "text": "the",
          "isWord": true
        }
      ],
      "add": []
    }
  ],
  "Moroni 9:3": [
    {
      "index": 44,
      "remove": [
        {
          "text": "Satan",
          "isWord": true
        }
      ],
      "add": [
        {
          "text": "satan",
          "isWord": true
        }
      ]
    }
  ],
  "Moroni 9:4": [
    {
      "index": 7,
      "remove": [
        {
          "text": "laboring",
          "isWord": true
        }
      ],
      "add": [
        {
          "text": "labouring",
          "isWord": true
        }
      ]
    }
  ],
  "Moroni 9:6": [
    {
      "index": 22,
      "remove": [
        {
          "text": "labor",
          "isWord": true
        }
      ],
      "add": [
        {
          "text": "labour",
          "isWord": true
        }
      ]
    },
    {
      "index": 25,
      "remove": [
        {
          "text": ":",
          "isWord": false
        }
      ],
      "add": [
        {
          "text": ";",
          "isWord": false
        }
      ]
    },
    {
      "index": 39,
      "remove": [
        {
          "text": "labor",
          "isWord": true
        }
      ],
      "add": [
        {
          "text": "labour",
          "isWord": true
        }
      ]
    },
    {
      "index": 53,
      "remove": [
        {
          "text": ":",
          "isWord": false
        }
      ],
      "add": [
        {
          "text": ";",
          "isWord": false
        }
      ]
    },
    {
      "index": 61,
      "remove": [
        {
          "text": "a",
          "isWord": true
        }
      ],
      "add": [
        {
          "text": "to",
          "isWord": true
        }
      ]
    },
    {
      "index": 63,
      "remove": [
        {
          "text": "labor",
          "isWord": true
        }
      ],
      "add": [
        {
          "text": "labour",
          "isWord": true
        }
      ]
    }
  ],
  "Moroni 9:10": [
    {
      "index": 3,
      "remove": [
        {
          "text": " ",
          "isWord": false
        },
        {
          "text": "that",
          "isWord": true
        }
      ],
      "add": []
    },
    {
      "index": 52,
      "remove": [
        {
          "text": " ",
          "isWord": false
        },
        {
          "text": "that",
          "isWord": true
        }
      ],
      "add": []
    }
  ],
  "Moroni 9:13": [
    {
      "index": 32,
      "remove": [
        {
          "text": "much",
          "isWord": true
        }
      ],
      "add": [
        {
          "text": "mnch",
          "isWord": true
        }
      ]
    }
  ],
  "Moroni 9:14": [
    {
      "index": 22,
      "remove": [
        {
          "text": "judgement",
          "isWord": true
        }
      ],
      "add": [
        {
          "text": "judgment",
          "isWord": true
        }
      ]
    }
  ],
  "Moroni 9:15": [
    {
      "index": 24,
      "remove": [
        {
          "text": "judgement",
          "isWord": true
        }
      ],
      "add": [
        {
          "text": "judgment",
          "isWord": true
        }
      ]
    }
  ],
  "Moroni 9:16": [
    {
      "index": 25,
      "remove": [
        {
          "text": "which",
          "isWord": true
        }
      ],
      "add": [
        {
          "text": "who",
          "isWord": true
        }
      ]
    }
  ],
  "Moroni 9:21": [
    {
      "index": 19,
      "remove": [
        {
          "text": ",",
          "isWord": false
        }
      ],
      "add": []
    }
  ],
  "Moroni 9:22": [
    {
      "index": 91,
      "remove": [
        {
          "text": ":",
          "isWord": false
        }
      ],
      "add": [
        {
          "text": ";",
          "isWord": false
        }
      ]
    }
  ],
  "Moroni 9:23": [
    {
      "index": 7,
      "remove": [
        {
          "text": ",",
          "isWord": false
        }
      ],
      "add": []
    }
  ],
  "Moroni 9:24": [
    {
      "index": 120,
      "remove": [
        {
          "text": ":",
          "isWord": false
        }
      ],
      "add": [
        {
          "text": ";",
          "isWord": false
        }
      ]
    }
  ],
  "Moroni 9:25": [
    {
      "index": 92,
      "remove": [
        {
          "text": ",",
          "isWord": false
        }
      ],
      "add": []
    },
    {
      "index": 136,
      "remove": [
        {
          "text": "forever",
          "isWord": true
        }
      ],
      "add": [
        {
          "text": "for ever",
          "isWord": true
        }
      ]
    }
  ],
  "Moroni 10:1": [
    {
      "index": 69,
      "remove": [
        {
          "text": "has",
          "isWord": true
        }
      ],
      "add": [
        {
          "text": "have",
          "isWord": true
        }
      ]
    }
  ],
  "Moroni 10:2": [
    {
      "index": 14,
      "remove": [
        {
          "text": " ",
          "isWord": false
        },
        {
          "text": "that",
          "isWord": true
        }
      ],
      "add": []
    }
  ],
  "Moroni 10:4": [
    {
      "index": 19,
      "remove": [
        {
          "text": "exhort",
          "isWord": true
        }
      ],
      "add": [
        {
          "text": "exhor",
          "isWord": true
        }
      ]
    },
    {
      "index": 36,
      "remove": [
        {
          "text": "Eternal",
          "isWord": true
        }
      ],
      "add": [
        {
          "text": "eternal",
          "isWord": true
        }
      ]
    },
    {
      "index": 100,
      "remove": [
        {
          "text": "and",
          "isWord": true
        },
        {
          "text": " ",
          "isWord": false
        }
      ],
      "add": []
    }
  ],
  "Moroni 10:7": [
    {
      "index": 56,
      "remove": [
        {
          "text": ":",
          "isWord": false
        }
      ],
      "add": [
        {
          "text": ";",
          "isWord": false
        }
      ]
    },
    {
      "index": 93,
      "remove": [
        {
          "text": ",",
          "isWord": false
        }
      ],
      "add": []
    },
    {
      "index": 102,
      "remove": [
        {
          "text": "forever",
          "isWord": true
        }
      ],
      "add": [
        {
          "text": "for ever",
          "isWord": true
        }
      ]
    }
  ],
  "Moroni 10:8": [
    {
      "index": 90,
      "remove": [
        {
          "text": "which",
          "isWord": true
        }
      ],
      "add": [
        {
          "text": "who",
          "isWord": true
        }
      ]
    },
    {
      "index": 99,
      "remove": [
        {
          "text": ":",
          "isWord": false
        }
      ],
      "add": [
        {
          "text": ";",
          "isWord": false
        }
      ]
    }
  ],
  "Moroni 10:13": [
    {
      "index": 8,
      "remove": [
        {
          "text": ",",
          "isWord": false
        }
      ],
      "add": []
    }
  ],
  "Moroni 10:16": [
    {
      "index": 22,
      "remove": [
        {
          "text": "diverse",
          "isWord": true
        }
      ],
      "add": [
        {
          "text": "divers",
          "isWord": true
        }
      ]
    }
  ],
  "Moroni 10:17": [
    {
      "index": 8,
      "remove": [
        {
          "text": "comes",
          "isWord": true
        }
      ],
      "add": [
        {
          "text": "come",
          "isWord": true
        }
      ]
    }
  ],
  "Moroni 10:19": [
    {
      "index": 42,
      "remove": [
        {
          "text": "forever",
          "isWord": true
        }
      ],
      "add": [
        {
          "text": "for ever",
          "isWord": true
        }
      ]
    }
  ],
  "Moroni 10:21": [
    {
      "index": 73,
      "remove": [
        {
          "text": ",",
          "isWord": false
        }
      ],
      "add": []
    }
  ],
  "Moroni 10:23": [
    {
      "index": 15,
      "remove": [
        {
          "text": "If",
          "isWord": true
        }
      ],
      "add": [
        {
          "text": "if",
          "isWord": true
        }
      ]
    }
  ],
  "Moroni 10:25": [
    {
      "index": 26,
      "remove": [
        {
          "text": ":",
          "isWord": false
        }
      ],
      "add": [
        {
          "text": ";",
          "isWord": false
        }
      ]
    }
  ],
  "Moroni 10:26": [
    {
      "index": 8,
      "remove": [
        {
          "text": "which",
          "isWord": true
        }
      ],
      "add": [
        {
          "text": "who",
          "isWord": true
        }
      ]
    }
  ],
  "Moroni 10:27": [
    {
      "index": 15,
      "remove": [
        {
          "text": ":",
          "isWord": false
        }
      ],
      "add": [
        {
          "text": ";",
          "isWord": false
        }
      ]
    },
    {
      "index": 63,
      "remove": [
        {
          "text": ":",
          "isWord": false
        }
      ],
      "add": [
        {
          "text": ",",
          "isWord": false
        }
      ]
    },
    {
      "index": 82,
      "remove": [
        {
          "text": "Did",
          "isWord": true
        }
      ],
      "add": [
        {
          "text": "did",
          "isWord": true
        }
      ]
    },
    {
      "index": 101,
      "remove": [
        {
          "text": "was",
          "isWord": true
        }
      ],
      "add": [
        {
          "text": "were",
          "isWord": true
        }
      ]
    },
    {
      "index": 145,
      "remove": [
        {
          "text": ",",
          "isWord": false
        }
      ],
      "add": [
        {
          "text": "?",
          "isWord": false
        }
      ]
    }
  ],
  "Moroni 10:30": [
    {
      "index": 62,
      "remove": [
        {
          "text": "—",
          "isWord": false
        }
      ],
      "add": []
    }
  ],
  "Moroni 10:31": [
    {
      "index": 35,
      "remove": [
        {
          "text": ",",
          "isWord": false
        }
      ],
      "add": []
    },
    {
      "index": 53,
      "remove": [
        {
          "text": ",",
          "isWord": false
        }
      ],
      "add": []
    },
    {
      "index": 63,
      "remove": [
        {
          "text": "forever",
          "isWord": true
        }
      ],
      "add": [
        {
          "text": "for ever",
          "isWord": true
        }
      ]
    },
    {
      "index": 91,
      "remove": [
        {
          "text": "Eternal",
          "isWord": true
        }
      ],
      "add": [
        {
          "text": "eternal",
          "isWord": true
        }
      ]
    },
    {
      "index": 94,
      "remove": [
        {
          "text": ",",
          "isWord": false
        }
      ],
      "add": []
    }
  ],
  "Moroni 10:32": [
    {
      "index": 32,
      "remove": [
        {
          "text": ";",
          "isWord": false
        }
      ],
      "add": [
        {
          "text": ",",
          "isWord": false
        }
      ]
    }
  ],
  "Moroni 10:34": [
    {
      "index": 51,
      "remove": [
        {
          "text": "reunite",
          "isWord": true
        }
      ],
      "add": [
        {
          "text": "re-unite",
          "isWord": true
        }
      ]
    },
    {
      "index": 98,
      "remove": [
        {
          "text": "Eternal",
          "isWord": true
        }
      ],
      "add": [
        {
          "text": "eternal",
          "isWord": true
        }
      ]
    }
  ]
}